ffmpeg_audio/__init__.py
ffmpeg_audio/exceptions.py
ffmpeg_audio/ffmpeg_audio.py
ffmpeg_audio-0.2.0.dist-info/licenses/LICENSE
ffmpeg_audio-0.2.0.dist-info/METADATA
ffmpeg_audio-0.2.0.dist-info/WHEEL
ffmpeg_audio-0.2.0.dist-info/top_level.txt
ffmpeg_audio-0.2.0.dist-info/RECORD
