Metadata-Version: 2.4
Name: ffmpeg-audio
Version: 0.2.0
Summary: A Python library for streaming audio/video files using FFmpeg with automatic resampling and channel mixing
License: MIT
Project-URL: Homepage, https://github.com/speech2srt/ffmpeg-audio
Project-URL: Repository, https://github.com/speech2srt/ffmpeg-audio
Project-URL: Issues, https://github.com/speech2srt/ffmpeg-audio/issues
Requires-Python: >=3.10
License-File: LICENSE
Requires-Dist: numpy>=1.26.4
Dynamic: license-file
